snakia/__init__.py
snakia/core/__init__.py
snakia/core/ecs/__init__.py
snakia/core/ecs/component.py
snakia/core/ecs/processor.py
snakia/core/ecs/system.py
snakia/core/engine.py
snakia/core/es/__init__.py
snakia/core/es/action.py
snakia/core/es/dispatcher.py
snakia/core/es/event.py
snakia/core/es/filter.py
snakia/core/es/handler.py
snakia/core/es/subscriber.py
snakia/core/except_manager.py
snakia/core/loader/__init__.py
snakia/core/loader/loadable.py
snakia/core/loader/loader.py
snakia/core/loader/meta.py
snakia/core/loader/plugin.py
snakia/core/loader/plugin_processor.py
snakia/core/rx/__init__.py
snakia/core/rx/async_bindable.py
snakia/core/rx/bindable.py
snakia/core/rx/chain.py
snakia/core/rx/combine.py
snakia/core/rx/concat.py
snakia/core/rx/const.py
snakia/core/rx/filter.py
snakia/core/rx/map.py
snakia/core/rx/merge.py
snakia/core/rx/value_changed.py
snakia/core/tui/__init__.py
snakia/core/tui/canvas.py
snakia/core/tui/char.py
snakia/core/tui/render/__init__.py
snakia/core/tui/render/ansi.py
snakia/core/tui/render/plain_text.py
snakia/core/tui/renderer.py
snakia/core/tui/widget.py
snakia/core/tui/widgets/__init__.py
snakia/core/tui/widgets/box.py
snakia/core/tui/widgets/container.py
snakia/core/tui/widgets/horizontal_split.py
snakia/core/tui/widgets/text.py
snakia/core/tui/widgets/vertical_split.py
snakia/decorators/__init__.py
snakia/decorators/inject_after.py
snakia/decorators/inject_before.py
snakia/decorators/inject_const.py
snakia/decorators/inject_replace.py
snakia/decorators/pass_exceptions.py
snakia/decorators/singleton.py
snakia/field/__init__.py
snakia/field/bool.py
snakia/field/field.py
snakia/field/float.py
snakia/field/int.py
snakia/field/str.py
snakia/platform/__init__.py
snakia/platform/android.py
snakia/platform/layer.py
snakia/platform/linux.py
snakia/platform/os.py
snakia/property/__init__.py
snakia/property/cell_property.py
snakia/property/classproperty.py
snakia/property/hook_property.py
snakia/property/initonly.py
snakia-0.1.0.dist-info/WHEEL
snakia-0.1.0.dist-info/METADATA
snakia-0.1.0.dist-info/RECORD
