Metadata-Version: 2.3
Name: snakia
Version: 0.1.0
Summary: idk
Author: rus07tam
Author-email: rus07tam <rus07tam@gmail.com>
Requires-Dist: networkx>=3.4.2
Requires-Dist: pydantic>=2.12.3
Requires-Python: >=3.12
